setup.py
simplesetup/__init__.py
simplesetup.egg-info/PKG-INFO
simplesetup.egg-info/SOURCES.txt
simplesetup.egg-info/dependency_links.txt
simplesetup.egg-info/top_level.txt