Metadata-Version: 1.1
Name: simplesetup
Version: 0.0.0
Summary: Routines to simplify setup.py
Home-page: https://github.com/hammerlab/simplesetup
Author: Tavi Nathanson
Author-email: tavi {dot} nathanson {at} gmail {dot} com
License: http://www.apache.org/licenses/LICENSE-2.0.html
Platform: UNKNOWN
Classifier: Development Status :: 3 - Alpha
Classifier: Environment :: Console
Classifier: Operating System :: OS Independent
Classifier: License :: OSI Approved :: Apache Software License
Classifier: Programming Language :: Python
Classifier: Topic :: Software Development :: Libraries
Classifier: Intended Audience :: Developers
